Added when in F1 branch
<?xml version="1.0" encoding="UTF-8"?>
<con:soapui-project id="d3293bc3-3dc1-4fe9-979b-a22131c9f20d" activeEnvironment="Default" name="Calculator" resourceRoot="" soapui-version="5.1.1" abortOnError="false" runType="SEQUENTIAL" xmlns:con="http://eviware.com/soapui/config"><con:settings/><con:interface xsi:type="con:WsdlInterface" id="837bed4d-4e08-4d86-974d-10838eec0e1a" wsaVersion="NONE" name="CalculatorSoap12" type="wsdl" bindingName="{http://tempuri.org/}CalculatorSoap12" soapVersion="1_2" anonymous="optional" definition="http://www.dneonline.com/calculator.asmx?WSDL" xmlns:xsi="http://www.w3.org/2001/XMLSchema-instance"><con:settings/><con:definitionCache type="TEXT" rootPart="http://www.dneonline.com/calculator.asmx?WSDL"><con:part><con:url>http://www.dneonline.com/calculator.asmx?WSDL</con:url><con:content><![CDATA[<wsdl:definitions targetNamespace="http://tempuri.org/" xmlns:soap="http://schemas.xmlsoap.org/wsdl/soap/" xmlns:tm="http://microsoft.com/wsdl/mime/textMatching/" xmlns:soapenc="http://schemas.xmlsoap.org/soap/encoding/" xmlns:mime="http://schemas.xmlsoap.org/wsdl/mime/" xmlns:tns="http://tempuri.org/" xmlns:s="http://www.w3.org/2001/XMLSchema" xmlns:soap12="http://schemas.xmlsoap.org/wsdl/soap12/" xmlns:http="http://schemas.xmlsoap.org/wsdl/http/" xmlns:wsdl="http://schemas.xmlsoap.org/wsdl/">
  <wsdl:types>
    <s:schema elementFormDefault="qualified" targetNamespace="http://tempuri.org/">
      <s:element name="Add"><!--more changes for assignment modified for amendment-->
        <s:complexType>
          <s:sequence>
            <s:element minOccurs="1" maxOccurs="1" name="intA" type="s:int"/>
            <s:element minOccurs="1" maxOccurs="1" name="intB" type="s:int"/>
          </s:sequence>
        </s:complexType>
      </s:element>
      <s:element name="AddResponse">
        <s:complexType>
          <s:sequence>
            <s:element minOccurs="1" maxOccurs="1" name="AddResult" type="s:int"/>
          </s:sequence>
        </s:complexType>
      </s:element>
      <s:element name="Subtract">
        <s:complexType>
          <s:sequence>
            <s:element minOccurs="1" maxOccurs="1" name="intA" type="s:int"/>
            <s:element minOccurs="1" maxOccurs="1" name="intB" type="s:int"/>
          </s:sequence>
        </s:complexType>
      </s:element>
      <s:element name="SubtractResponse">
        <s:complexType>
          <s:sequence>
            <s:element minOccurs="1" maxOccurs="1" name="SubtractResult" type="s:int"/>
          </s:sequence>
        </s:complexType>
      </s:element>
      <s:element name="Multiply">
        <s:complexType>
          <s:sequence>
            <s:element minOccurs="1" maxOccurs="1" name="intA" type="s:int"/>
            <s:element minOccurs="1" maxOccurs="1" name="intB" type="s:int"/>
          </s:sequence>
        </s:complexType>
      </s:element>
      <s:element name="MultiplyResponse">
        <s:complexType>
          <s:sequence>
            <s:element minOccurs="1" maxOccurs="1" name="MultiplyResult" type="s:int"/>
          </s:sequence>
        </s:complexType>
      </s:element>
      <s:element name="Divide">
        <s:complexType>
          <s:sequence>
            <s:element minOccurs="1" maxOccurs="1" name="intA" type="s:int"/>
            <s:element minOccurs="1" maxOccurs="1" name="intB" type="s:int"/>
          </s:sequence>
        </s:complexType>
      </s:element>
      <s:element name="DivideResponse">
        <s:complexType>
          <s:sequence>
            <s:element minOccurs="1" maxOccurs="1" name="DivideResult" type="s:int"/>
          </s:sequence>
        </s:complexType>
      </s:element>
    </s:schema>
  </wsdl:types>
  <wsdl:message name="AddSoapIn">
    <wsdl:part name="parameters" element="tns:Add"/>
  </wsdl:message>
  <wsdl:message name="AddSoapOut">
    <wsdl:part name="parameters" element="tns:AddResponse"/>
  </wsdl:message>
  <wsdl:message name="SubtractSoapIn">
    <wsdl:part name="parameters" element="tns:Subtract"/>
  </wsdl:message>
  <wsdl:message name="SubtractSoapOut">
    <wsdl:part name="parameters" element="tns:SubtractResponse"/>
  </wsdl:message>
  <wsdl:message name="MultiplySoapIn">
    <wsdl:part name="parameters" element="tns:Multiply"/>
  </wsdl:message>
  <wsdl:message name="MultiplySoapOut">
    <wsdl:part name="parameters" element="tns:MultiplyResponse"/>
  </wsdl:message>
  <wsdl:message name="DivideSoapIn">
    <wsdl:part name="parameters" element="tns:Divide"/>
  </wsdl:message>
  <wsdl:message name="DivideSoapOut">
    <wsdl:part name="parameters" element="tns:DivideResponse"/>
  </wsdl:message>
  <wsdl:portType name="CalculatorSoap">
    <wsdl:operation name="Add">
      <wsdl:documentation>Adds two integers. This is a test WebService. ©DNE Online</wsdl:documentation>
      <wsdl:input message="tns:AddSoapIn"/>
      <wsdl:output message="tns:AddSoapOut"/>
    </wsdl:operation>
    <wsdl:operation name="Subtract">
      <wsdl:input message="tns:SubtractSoapIn"/>
      <wsdl:output message="tns:SubtractSoapOut"/>
    </wsdl:operation>
    <wsdl:operation name="Multiply">
      <wsdl:input message="tns:MultiplySoapIn"/>
      <wsdl:output message="tns:MultiplySoapOut"/>
    </wsdl:operation>
    <wsdl:operation name="Divide">
      <wsdl:input message="tns:DivideSoapIn"/>
      <wsdl:output message="tns:DivideSoapOut"/>
    </wsdl:operation>
  </wsdl:portType>
  <wsdl:binding name="CalculatorSoap" type="tns:CalculatorSoap">
    <soap:binding transport="http://schemas.xmlsoap.org/soap/http"/>
    <wsdl:operation name="Add">
      <soap:operation soapAction="http://tempuri.org/Add" style="document"/>
      <wsdl:input>
        <soap:body use="literal"/>
      </wsdl:input>
      <wsdl:output>
        <soap:body use="literal"/>
      </wsdl:output>
    </wsdl:operation>
    <wsdl:operation name="Subtract">
      <soap:operation soapAction="http://tempuri.org/Subtract" style="document"/>
      <wsdl:input>
        <soap:body use="literal"/>
      </wsdl:input>
      <wsdl:output>
        <soap:body use="literal"/>
      </wsdl:output>
    </wsdl:operation>
    <wsdl:operation name="Multiply">
      <soap:operation soapAction="http://tempuri.org/Multiply" style="document"/>
      <wsdl:input>
        <soap:body use="literal"/>
      </wsdl:input>
      <wsdl:output>
        <soap:body use="literal"/>
      </wsdl:output>
    </wsdl:operation>
    <wsdl:operation name="Divide">
      <soap:operation soapAction="http://tempuri.org/Divide" style="document"/>
      <wsdl:input>
        <soap:body use="literal"/>
      </wsdl:input>
      <wsdl:output>
        <soap:body use="literal"/>
      </wsdl:output>
    </wsdl:operation>
  </wsdl:binding>
  <wsdl:binding name="CalculatorSoap12" type="tns:CalculatorSoap">
    <soap12:binding transport="http://schemas.xmlsoap.org/soap/http"/>
    <wsdl:operation name="Add">
      <soap12:operation soapAction="http://tempuri.org/Add" style="document"/>
      <wsdl:input>
        <soap12:body use="literal"/>
      </wsdl:input>
      <wsdl:output>
        <soap12:body use="literal"/>
      </wsdl:output>
    </wsdl:operation>
    <wsdl:operation name="Subtract">
      <soap12:operation soapAction="http://tempuri.org/Subtract" style="document"/>
      <wsdl:input>
        <soap12:body use="literal"/>
      </wsdl:input>
      <wsdl:output>
        <soap12:body use="literal"/>
      </wsdl:output>
    </wsdl:operation>
    <wsdl:operation name="Multiply">
      <soap12:operation soapAction="http://tempuri.org/Multiply" style="document"/>
      <wsdl:input>
        <soap12:body use="literal"/>
      </wsdl:input>
      <wsdl:output>
        <soap12:body use="literal"/>
      </wsdl:output>
    </wsdl:operation>
    <wsdl:operation name="Divide">
      <soap12:operation soapAction="http://tempuri.org/Divide" style="document"/>
      <wsdl:input>
        <soap12:body use="literal"/>
      </wsdl:input>
      <wsdl:output>
        <soap12:body use="literal"/>
      </wsdl:output>
    </wsdl:operation>
  </wsdl:binding>
  <wsdl:service name="Calculator">
    <wsdl:port name="CalculatorSoap" binding="tns:CalculatorSoap">
      <soap:address location="http://www.dneonline.com/calculator.asmx"/>
    </wsdl:port>
    <wsdl:port name="CalculatorSoap12" binding="tns:CalculatorSoap12">
      <soap12:address location="http://www.dneonline.com/calculator.asmx"/>
    </wsdl:port>
  </wsdl:service>
</wsdl:definitions>]]></con:content><con:type>http://schemas.xmlsoap.org/wsdl/</con:type></con:part></con:definitionCache><con:endpoints><con:endpoint>http://www.dneonline.com/calculator.asmx</con:endpoint></con:endpoints><con:operation id="3a69c099-4d3f-4cbd-ba01-02dc0715d8d0" isOneWay="false" action="http://tempuri.org/Add" name="Add" bindingOperationName="Add" type="Request-Response" inputName="" receivesAttachments="false" sendsAttachments="false" anonymous="optional"><con:settings/><con:call id="e6473ebd-e67b-4e62-b326-782825f824d9" name="Request 1"><con:settings/><con:encoding>UTF-8</con:encoding><con:endpoint>http://www.dneonline.com/calculator.asmx</con:endpoint><con:request><![CDATA[<soap:Envelope xmlns:soap="http://www.w3.org/2003/05/soap-envelope" xmlns:tem="http://tempuri.org/">\r
   <soap:Header/>\r
   <soap:Body>\r
      <tem:Add>\r
         <tem:intA>?</tem:intA>\r
         <tem:intB>?</tem:intB>\r
      </tem:Add>\r
   </soap:Body>\r
</soap:Envelope>]]></con:request><con:wsaConfig mustUnderstand="NONE" version="200508" action="http://tempuri.org/CalculatorSoap/AddRequest"/></con:call></con:operation><con:operation id="0a387cf9-0318-40b5-b9e8-5d4c4e944692" isOneWay="false" action="http://tempuri.org/Divide" name="Divide" bindingOperationName="Divide" type="Request-Response" inputName="" receivesAttachments="false" sendsAttachments="false" anonymous="optional"><con:settings/><con:call id="ebbcabd6-9b56-404c-be95-6b6af1a55758" name="Request 1"><con:settings/><con:encoding>UTF-8</con:encoding><con:endpoint>http://www.dneonline.com/calculator.asmx</con:endpoint><con:request><![CDATA[<soap:Envelope xmlns:soap="http://www.w3.org/2003/05/soap-envelope" xmlns:tem="http://tempuri.org/">\r
   <soap:Header/>\r
   <soap:Body>\r
      <tem:Divide>\r
         <tem:intA>?</tem:intA>\r
         <tem:intB>?</tem:intB>\r
      </tem:Divide>\r
   </soap:Body>\r
</soap:Envelope>]]></con:request><con:wsaConfig mustUnderstand="NONE" version="200508" action="http://tempuri.org/CalculatorSoap/DivideRequest"/></con:call></con:operation><con:operation id="b76e2b64-6044-43b5-b14f-50735e280ae8" isOneWay="false" action="http://tempuri.org/Multiply" name="Multiply" bindingOperationName="Multiply" type="Request-Response" inputName="" receivesAttachments="false" sendsAttachments="false" anonymous="optional"><con:settings/><con:call id="2bd16aec-099a-4cbc-9e58-6ea26a20704c" name="Request 1"><con:settings/><con:encoding>UTF-8</con:encoding><con:endpoint>http://www.dneonline.com/calculator.asmx</con:endpoint><con:request><![CDATA[<soap:Envelope xmlns:soap="http://www.w3.org/2003/05/soap-envelope" xmlns:tem="http://tempuri.org/">\r
   <soap:Header/>\r
   <soap:Body>\r
      <tem:Multiply>\r
         <tem:intA>?</tem:intA>\r
         <tem:intB>?</tem:intB>\r
      </tem:Multiply>\r
   </soap:Body>\r
</soap:Envelope>]]></con:request><con:wsaConfig mustUnderstand="NONE" version="200508" action="http://tempuri.org/CalculatorSoap/MultiplyRequest"/></con:call></con:operation><con:operation id="9d96b3a9-72a7-4627-9b41-e9d9b5f3fdef" isOneWay="false" action="http://tempuri.org/Subtract" name="Subtract" bindingOperationName="Subtract" type="Request-Response" inputName="" receivesAttachments="false" sendsAttachments="false" anonymous="optional"><con:settings/><con:call id="4003b9e8-ff3b-42e8-a979-33d71555cc43" name="Request 1"><con:settings/><con:encoding>UTF-8</con:encoding><con:endpoint>http://www.dneonline.com/calculator.asmx</con:endpoint><con:request><![CDATA[<soap:Envelope xmlns:soap="http://www.w3.org/2003/05/soap-envelope" xmlns:tem="http://tempuri.org/">\r
   <soap:Header/>\r
   <soap:Body>\r
      <tem:Subtract>\r
         <tem:intA>?</tem:intA>\r
         <tem:intB>?</tem:intB>\r
      </tem:Subtract>\r
   </soap:Body>\r
</soap:Envelope>]]></con:request><con:wsaConfig mustUnderstand="NONE" version="200508" action="http://tempuri.org/CalculatorSoap/SubtractRequest"/></con:call></con:operation></con:interface><con:interface xsi:type="con:WsdlInterface" id="7e4c87ba-6cc7-415d-a8bb-5390b9b720ee" wsaVersion="NONE" name="CalculatorSoap" type="wsdl" bindingName="{http://tempuri.org/}CalculatorSoap" soapVersion="1_1" anonymous="optional" definition="http://www.dneonline.com/calculator.asmx?WSDL" xmlns:xsi="http://www.w3.org/2001/XMLSchema-instance"><con:settings/><con:definitionCache type="TEXT" rootPart="http://www.dneonline.com/calculator.asmx?WSDL"><con:part><con:url>http://www.dneonline.com/calculator.asmx?WSDL</con:url><con:content><![CDATA[<wsdl:definitions targetNamespace="http://tempuri.org/" xmlns:soap="http://schemas.xmlsoap.org/wsdl/soap/" xmlns:tm="http://microsoft.com/wsdl/mime/textMatching/" xmlns:soapenc="http://schemas.xmlsoap.org/soap/encoding/" xmlns:mime="http://schemas.xmlsoap.org/wsdl/mime/" xmlns:tns="http://tempuri.org/" xmlns:s="http://www.w3.org/2001/XMLSchema" xmlns:soap12="http://schemas.xmlsoap.org/wsdl/soap12/" xmlns:http="http://schemas.xmlsoap.org/wsdl/http/" xmlns:wsdl="http://schemas.xmlsoap.org/wsdl/">
  <wsdl:types>
    <s:schema elementFormDefault="qualified" targetNamespace="http://tempuri.org/">
      <s:element name="Add">
        <s:complexType>
          <s:sequence>
            <s:element minOccurs="1" maxOccurs="1" name="intA" type="s:int"/>
            <s:element minOccurs="1" maxOccurs="1" name="intB" type="s:int"/>
          </s:sequence>
        </s:complexType>
      </s:element>
      <s:element name="AddResponse">
        <s:complexType>
          <s:sequence>
            <s:element minOccurs="1" maxOccurs="1" name="AddResult" type="s:int"/>
          </s:sequence>
        </s:complexType>
      </s:element>
      <s:element name="Subtract">
        <s:complexType>
          <s:sequence>
            <s:element minOccurs="1" maxOccurs="1" name="intA" type="s:int"/>
            <s:element minOccurs="1" maxOccurs="1" name="intB" type="s:int"/>
          </s:sequence>
        </s:complexType>
      </s:element>
      <s:element name="SubtractResponse">
        <s:complexType>
          <s:sequence>
            <s:element minOccurs="1" maxOccurs="1" name="SubtractResult" type="s:int"/>
          </s:sequence>
        </s:complexType>
      </s:element>
      <s:element name="Multiply">
        <s:complexType>
          <s:sequence>
            <s:element minOccurs="1" maxOccurs="1" name="intA" type="s:int"/>
            <s:element minOccurs="1" maxOccurs="1" name="intB" type="s:int"/>
          </s:sequence>
        </s:complexType>
      </s:element>
      <s:element name="MultiplyResponse">
        <s:complexType>
          <s:sequence>
            <s:element minOccurs="1" maxOccurs="1" name="MultiplyResult" type="s:int"/>
          </s:sequence>
        </s:complexType>
      </s:element>
      <s:element name="Divide">
        <s:complexType>
          <s:sequence>
            <s:element minOccurs="1" maxOccurs="1" name="intA" type="s:int"/>
            <s:element minOccurs="1" maxOccurs="1" name="intB" type="s:int"/>
          </s:sequence>
        </s:complexType>
      </s:element>
      <s:element name="DivideResponse">
        <s:complexType>
          <s:sequence>
            <s:element minOccurs="1" maxOccurs="1" name="DivideResult" type="s:int"/>
          </s:sequence>
        </s:complexType>
      </s:element>
    </s:schema>
  </wsdl:types>
  <wsdl:message name="AddSoapIn">
    <wsdl:part name="parameters" element="tns:Add"/>
  </wsdl:message>
  <wsdl:message name="AddSoapOut">
    <wsdl:part name="parameters" element="tns:AddResponse"/>
  </wsdl:message>
  <wsdl:message name="SubtractSoapIn">
    <wsdl:part name="parameters" element="tns:Subtract"/>
  </wsdl:message>
  <wsdl:message name="SubtractSoapOut">
    <wsdl:part name="parameters" element="tns:SubtractResponse"/>
  </wsdl:message>
  <wsdl:message name="MultiplySoapIn">
    <wsdl:part name="parameters" element="tns:Multiply"/>
  </wsdl:message>
  <wsdl:message name="MultiplySoapOut">
    <wsdl:part name="parameters" element="tns:MultiplyResponse"/>
  </wsdl:message>
  <wsdl:message name="DivideSoapIn">
    <wsdl:part name="parameters" element="tns:Divide"/>
  </wsdl:message>
  <wsdl:message name="DivideSoapOut">
    <wsdl:part name="parameters" element="tns:DivideResponse"/>
  </wsdl:message>
  <wsdl:portType name="CalculatorSoap">
    <wsdl:operation name="Add">
      <wsdl:documentation>Adds two integers. This is a test WebService. ©DNE Online</wsdl:documentation>
      <wsdl:input message="tns:AddSoapIn"/>
      <wsdl:output message="tns:AddSoapOut"/>
    </wsdl:operation>
    <wsdl:operation name="Subtract">
      <wsdl:input message="tns:SubtractSoapIn"/>
      <wsdl:output message="tns:SubtractSoapOut"/>
    </wsdl:operation>
    <wsdl:operation name="Multiply">
      <wsdl:input message="tns:MultiplySoapIn"/>
      <wsdl:output message="tns:MultiplySoapOut"/>
    </wsdl:operation>
    <wsdl:operation name="Divide">
      <wsdl:input message="tns:DivideSoapIn"/>
      <wsdl:output message="tns:DivideSoapOut"/>
    </wsdl:operation>
  </wsdl:portType>
  <wsdl:binding name="CalculatorSoap" type="tns:CalculatorSoap">
    <soap:binding transport="http://schemas.xmlsoap.org/soap/http"/>
    <wsdl:operation name="Add">
      <soap:operation soapAction="http://tempuri.org/Add" style="document"/>
      <wsdl:input>
        <soap:body use="literal"/>
      </wsdl:input>
      <wsdl:output>
        <soap:body use="literal"/>
      </wsdl:output>
    </wsdl:operation>
    <wsdl:operation name="Subtract">
      <soap:operation soapAction="http://tempuri.org/Subtract" style="document"/>
      <wsdl:input>
        <soap:body use="literal"/>
      </wsdl:input>
      <wsdl:output>
        <soap:body use="literal"/>
      </wsdl:output>
    </wsdl:operation>
    <wsdl:operation name="Multiply">
      <soap:operation soapAction="http://tempuri.org/Multiply" style="document"/>
      <wsdl:input>
        <soap:body use="literal"/>
      </wsdl:input>
      <wsdl:output>
        <soap:body use="literal"/>
      </wsdl:output>
    </wsdl:operation>
    <wsdl:operation name="Divide">
      <soap:operation soapAction="http://tempuri.org/Divide" style="document"/>
      <wsdl:input>
        <soap:body use="literal"/>
      </wsdl:input>
      <wsdl:output>
        <soap:body use="literal"/>
      </wsdl:output>
    </wsdl:operation>
  </wsdl:binding>
  <wsdl:binding name="CalculatorSoap12" type="tns:CalculatorSoap">
    <soap12:binding transport="http://schemas.xmlsoap.org/soap/http"/>
    <wsdl:operation name="Add">
      <soap12:operation soapAction="http://tempuri.org/Add" style="document"/>
      <wsdl:input>
        <soap12:body use="literal"/>
      </wsdl:input>
      <wsdl:output>
        <soap12:body use="literal"/>
      </wsdl:output>
    </wsdl:operation>
    <wsdl:operation name="Subtract">
      <soap12:operation soapAction="http://tempuri.org/Subtract" style="document"/>
      <wsdl:input>
        <soap12:body use="literal"/>
      </wsdl:input>
      <wsdl:output>
        <soap12:body use="literal"/>
      </wsdl:output>
    </wsdl:operation>
    <wsdl:operation name="Multiply">
      <soap12:operation soapAction="http://tempuri.org/Multiply" style="document"/>
      <wsdl:input>
        <soap12:body use="literal"/>
      </wsdl:input>
      <wsdl:output>
        <soap12:body use="literal"/>
      </wsdl:output>
    </wsdl:operation>
    <wsdl:operation name="Divide">
      <soap12:operation soapAction="http://tempuri.org/Divide" style="document"/>
      <wsdl:input>
        <soap12:body use="literal"/>
      </wsdl:input>
      <wsdl:output>
        <soap12:body use="literal"/>
      </wsdl:output>
    </wsdl:operation>
  </wsdl:binding>
  <wsdl:service name="Calculator">
    <wsdl:port name="CalculatorSoap" binding="tns:CalculatorSoap">
      <soap:address location="http://www.dneonline.com/calculator.asmx"/>
    </wsdl:port>
    <wsdl:port name="CalculatorSoap12" binding="tns:CalculatorSoap12">
      <soap12:address location="http://www.dneonline.com/calculator.asmx"/>
    </wsdl:port>
  </wsdl:service>
</wsdl:definitions>]]></con:content><con:type>http://schemas.xmlsoap.org/wsdl/</con:type></con:part></con:definitionCache><con:endpoints><con:endpoint>http://www.dneonline.com/calculator.asmx</con:endpoint></con:endpoints><con:operation id="c96b2a21-5c2b-4e35-bd8b-855055657e67" isOneWay="false" action="http://tempuri.org/Add" name="Add" bindingOperationName="Add" type="Request-Response" inputName="" receivesAttachments="false" sendsAttachments="false" anonymous="optional"><con:settings/><con:call id="d6794c6a-80c3-44a2-ab95-ed0c5c726cf6" name="Request 1"><con:settings/><con:encoding>UTF-8</con:encoding><con:endpoint>http://www.dneonline.com/calculator.asmx</con:endpoint><con:request><![CDATA[<soapenv:Envelope xmlns:soapenv="http://schemas.xmlsoap.org/soap/envelope/" xmlns:tem="http://tempuri.org/">\r
   <soapenv:Header/>\r
   <soapenv:Body>\r
      <tem:Add>\r
         <tem:intA>?</tem:intA>\r
         <tem:intB>?</tem:intB>\r
      </tem:Add>\r
   </soapenv:Body>\r
</soapenv:Envelope>]]></con:request><con:credentials><con:authType>No Authorization</con:authType></con:credentials><con:jmsConfig JMSDeliveryMode="PERSISTENT"/><con:jmsPropertyConfig/><con:wsaConfig mustUnderstand="NONE" version="200508" action="http://tempuri.org/Add"/><con:wsrmConfig version="1.2"/></con:call></con:operation><con:operation id="201456b6-718e-468b-8ebe-643bbe5eea5b" isOneWay="false" action="http://tempuri.org/Divide" name="Divide" bindingOperationName="Divide" type="Request-Response" inputName="" receivesAttachments="false" sendsAttachments="false" anonymous="optional"><con:settings/><con:call id="7883b9b1-40ee-4405-8587-a6870e9e15f1" name="Request 1"><con:settings/><con:encoding>UTF-8</con:encoding><con:endpoint>http://www.dneonline.com/calculator.asmx</con:endpoint><con:request><![CDATA[<soapenv:Envelope xmlns:soapenv="http://schemas.xmlsoap.org/soap/envelope/" xmlns:tem="http://tempuri.org/">\r
   <soapenv:Header/>\r
   <soapenv:Body>\r
      <tem:Divide>\r
         <tem:intA>?</tem:intA>\r
         <tem:intB>?</tem:intB>\r
      </tem:Divide>\r
   </soapenv:Body>\r
</soapenv:Envelope>]]></con:request><con:wsaConfig mustUnderstand="NONE" version="200508" action="http://tempuri.org/Divide"/></con:call></con:operation><con:operation id="2b7e7670-5983-468b-95bc-e06507158399" isOneWay="false" action="http://tempuri.org/Multiply" name="Multiply" bindingOperationName="Multiply" type="Request-Response" inputName="" receivesAttachments="false" sendsAttachments="false" anonymous="optional"><con:settings/><con:call id="264616b6-b6aa-4af3-abbf-2dcd1a1f469e" name="Request 1"><con:settings/><con:encoding>UTF-8</con:encoding><con:endpoint>http://www.dneonline.com/calculator.asmx</con:endpoint><con:request><![CDATA[<soapenv:Envelope xmlns:soapenv="http://schemas.xmlsoap.org/soap/envelope/" xmlns:tem="http://tempuri.org/">\r
   <soapenv:Header/>\r
   <soapenv:Body>\r
      <tem:Multiply>\r
         <tem:intA>?</tem:intA>\r
         <tem:intB>?</tem:intB>\r
      </tem:Multiply>\r
   </soapenv:Body>\r
</soapenv:Envelope>]]></con:request><con:wsaConfig mustUnderstand="NONE" version="200508" action="http://tempuri.org/Multiply"/></con:call></con:operation><con:operation id="a95848b7-a8d7-450f-b239-51d3025c6acc" isOneWay="false" action="http://tempuri.org/Subtract" name="Subtract" bindingOperationName="Subtract" type="Request-Response" inputName="" receivesAttachments="false" sendsAttachments="false" anonymous="optional"><con:settings/><con:call id="c934e405-8c49-4710-b5c0-b2dc6970c9a3" name="Request 1"><con:settings/><con:encoding>UTF-8</con:encoding><con:endpoint>http://www.dneonline.com/calculator.asmx</con:endpoint><con:request><![CDATA[<soapenv:Envelope xmlns:soapenv="http://schemas.xmlsoap.org/soap/envelope/" xmlns:tem="http://tempuri.org/">\r
   <soapenv:Header/>\r
   <soapenv:Body>\r
      <tem:Subtract>\r
         <tem:intA>?</tem:intA>\r
         <tem:intB>?</tem:intB>\r
      </tem:Subtract>\r
   </soapenv:Body>\r
</soapenv:Envelope>]]></con:request><con:wsaConfig mustUnderstand="NONE" version="200508" action="http://tempuri.org/Subtract"/></con:call></con:operation></con:interface><con:testSuite id="3e35fd29-7ad7-49ab-97a4-49edd3802468" name="TestSuite 1"><con:settings/><con:runType>SEQUENTIAL</con:runType><con:testCase id="cb8bb425-5922-4637-9ca1-682196a24e53" failOnError="false" failTestCaseOnErrors="true" keepSession="false" maxResults="0" name="TestCase 1(AddSub)" searchProperties="true" timeout="0" wsrmEnabled="false" wsrmVersion="1.0" wsrmAckTo="" amfAuthorisation="false" amfEndpoint="" amfLogin="" amfPassword=""><con:settings/><con:testStep type="properties" name="Properties" id="6f450b2c-292f-4fab-a9cc-d36ce2643755"><con:settings/><con:config xsi:type="con:PropertiesStep" saveFirst="true" xmlns:xsi="http://www.w3.org/2001/XMLSchema-instance"><con:properties><con:property><con:name>A</con:name><con:value>200</con:value></con:property><con:property><con:name>B</con:name><con:value>100</con:value></con:property></con:properties></con:config></con:testStep><con:testStep type="datasource" name="DataSource1" id="72a4349b-3846-4a82-84bf-ee2d89263047"><con:settings/><con:config xsi:type="con:DataSourceStep" xmlns:xsi="http://www.w3.org/2001/XMLSchema-instance"><con:dataSource type="Grid"><con:configuration><row><![CDATA[<xml-fragment><con:entry xmlns:con="http://eviware.com/soapui/config">10</con:entry><con:entry xmlns:con="http://eviware.com/soapui/config">5</con:entry></xml-fragment>]]></row><row><![CDATA[<xml-fragment><con:entry xmlns:con="http://eviware.com/soapui/config">20</con:entry><con:entry xmlns:con="http://eviware.com/soapui/config">15</con:entry></xml-fragment>]]></row><row><![CDATA[<xml-fragment><con:entry xmlns:con="http://eviware.com/soapui/config">30</con:entry><con:entry xmlns:con="http://eviware.com/soapui/config">25</con:entry></xml-fragment>]]></row><row><![CDATA[<xml-fragment><con:entry xmlns:con="http://eviware.com/soapui/config">40</con:entry><con:entry xmlns:con="http://eviware.com/soapui/config">35</con:entry></xml-fragment>]]></row></con:configuration></con:dataSource><con:property>AddVal1</con:property><con:property>AddVal2</con:property><con:restartOnRun>true</con:restartOnRun></con:config></con:testStep><con:testStep type="request" name="Addition" id="24180752-beb3-4245-8abc-a81342a0d484"><con:settings/><con:config xsi:type="con:RequestStep" xmlns:xsi="http://www.w3.org/2001/XMLSchema-instance"><con:interface>CalculatorSoap12</con:interface><con:operation>Add</con:operation><con:request name="Addition" id="cc95db88-9bd6-4b8b-a7fd-d370b103c25f"><con:settings><con:setting id="com.eviware.soapui.impl.wsdl.WsdlRequest@request-headers">&lt;xml-fragment/></con:setting></con:settings><con:encoding>UTF-8</con:encoding><con:endpoint>http://www.dneonline.com/calculator.asmx</con:endpoint><con:request><![CDATA[<soap:Envelope xmlns:soap="http://www.w3.org/2003/05/soap-envelope" xmlns:tem="http://tempuri.org/">
   <soap:Header/>
   <soap:Body>
      <tem:Add>
         <tem:intA>${DataSource1#AddVal1}</tem:intA>
         <tem:intB>${DataSource1#AddVal2}</tem:intB>
      </tem:Add>
   </soap:Body>
</soap:Envelope>]]></con:request><con:assertion type="SOAP Response" id="4e394200-bb89-498d-9b04-cfa350d62187"/><con:assertion type="Simple Contains" id="c4535770-bb6c-4488-b4e0-1813d09caf18" name="Contains" disabled="true"><con:configuration><token>300</token><ignoreCase>false</ignoreCase><useRegEx>false</useRegEx></con:configuration></con:assertion><con:credentials><con:authType>No Authorization</con:authType></con:credentials><con:jmsConfig JMSDeliveryMode="PERSISTENT"/><con:jmsPropertyConfig/><con:wsaConfig mustUnderstand="NONE" version="200508"/><con:wsrmConfig version="1.2"/></con:request></con:config></con:testStep><con:testStep type="datasourceloop" name="DataSourceLoop1" id="1c623aa8-1365-4687-8cf8-9557279b8da0"><con:settings/><con:config><dataSourceStep>DataSource1</dataSourceStep><targetStep>Addition</targetStep></con:config></con:testStep><con:testStep type="delay" name="Delay(Between Steps)" id="279d021c-30d6-43a3-9d57-37ee7ab282f8"><con:settings/><con:config><delay>10000</delay></con:config></con:testStep><con:testStep type="manualTestStep" name="Manual TestStep(Ex-Restart Server)" id="eb606e51-8eab-4d29-ac84-ff8503be6c20"><con:description>Restart Server
Validate DB</con:description><con:settings/><con:config xsi:type="con:ManualTestStep" xmlns:xsi="http://www.w3.org/2001/XMLSchema-instance"><con:expectedResult>Step Should Pass</con:expectedResult></con:config></con:testStep><con:testStep type="datasource" name="DataSource2" id="bb44e03b-b77a-470a-8c4d-1378df9d6df0"><con:settings/><con:config xsi:type="con:DataSourceStep" xmlns:xsi="http://www.w3.org/2001/XMLSchema-instance"><con:dataSource type="Excel"><con:configuration><file>C:/Users/bapuc/OneDrive/Documents/Selenium_Nitin Sir_Videos/API Testing/DataSource1.xlsx</file><worksheet>Substraction</worksheet><cell>A2</cell><ignoreEmpty>false</ignoreEmpty></con:configuration></con:dataSource><con:property>SubVal1</con:property><con:property>SubVal2</con:property><con:restartOnRun>true</con:restartOnRun></con:config></con:testStep><con:testStep type="request" name="Substraction" id="577e142a-4716-4c55-95d6-31acf0460e3f"><con:settings/><con:config xsi:type="con:RequestStep" xmlns:xsi="http://www.w3.org/2001/XMLSchema-instance"><con:interface>CalculatorSoap12</con:interface><con:operation>Subtract</con:operation><con:request name="Substraction" id="aafa3ed5-ed75-405b-92e2-e67877985385"><con:settings><con:setting id="com.eviware.soapui.impl.wsdl.WsdlRequest@request-headers">&lt;xml-fragment/></con:setting></con:settings><con:encoding>UTF-8</con:encoding><con:endpoint>http://www.dneonline.com/calculator.asmx</con:endpoint><con:request><![CDATA[<soap:Envelope xmlns:soap="http://www.w3.org/2003/05/soap-envelope" xmlns:tem="http://tempuri.org/">
   <soap:Header/>
   <soap:Body>
      <tem:Subtract>
         <tem:intA>${DataSource2#SubVal1}</tem:intA>
         <tem:intB>${DataSource2#SubVal2}</tem:intB>

      </tem:Subtract>
   </soap:Body>
</soap:Envelope>]]></con:request><con:assertion type="SOAP Response" id="bdb50ceb-64de-46f9-8836-2493593d5a21"/><con:assertion type="Simple NotContains" id="518c4511-d5b6-495e-ba52-2e9bbbbb0c03" name="Not Contains"><con:configuration><token>1000</token><ignoreCase>false</ignoreCase><useRegEx>false</useRegEx></con:configuration></con:assertion><con:credentials><con:authType>No Authorization</con:authType></con:credentials><con:jmsConfig JMSDeliveryMode="PERSISTENT"/><con:jmsPropertyConfig/><con:wsaConfig mustUnderstand="NONE" version="200508"/><con:wsrmConfig version="1.2"/></con:request></con:config></con:testStep><con:testStep type="datasourceloop" name="DataSourceLoop2" id="1567256c-b1fd-454f-9c94-7176fa6cca5d"><con:settings/><con:config><dataSourceStep>DataSource2</dataSourceStep><targetStep>Substraction</targetStep></con:config></con:testStep><con:testStep type="calltestcase" name="Run TestCase(multiply)" id="17b08462-3d0c-4eea-944d-2b91224ed4d1"><con:settings/><con:config xsi:type="con:RunTestCaseStep" xmlns:xsi="http://www.w3.org/2001/XMLSchema-instance"><con:targetTestCase>b86731c1-b497-4ca5-a282-053fc91e0567</con:targetTestCase><con:properties><con:property><con:name>I</con:name></con:property></con:properties><con:returnProperties/><con:runMode>PARALLELL</con:runMode></con:config></con:testStep><con:testStep type="datasource" name="Copy of DataSource1" id="942101cf-6a2a-40fd-997d-4ca5f5771bcc"><con:settings/><con:config xsi:type="con:DataSourceStep" xmlns:xsi="http://www.w3.org/2001/XMLSchema-instance"><con:dataSource type="Grid"><con:configuration><row><![CDATA[<xml-fragment><con:entry xmlns:con="http://eviware.com/soapui/config">10</con:entry><con:entry xmlns:con="http://eviware.com/soapui/config">5</con:entry></xml-fragment>]]></row><row><![CDATA[<xml-fragment><con:entry xmlns:con="http://eviware.com/soapui/config">20</con:entry><con:entry xmlns:con="http://eviware.com/soapui/config">15</con:entry></xml-fragment>]]></row><row><![CDATA[<xml-fragment><con:entry xmlns:con="http://eviware.com/soapui/config">30</con:entry><con:entry xmlns:con="http://eviware.com/soapui/config">25</con:entry></xml-fragment>]]></row><row><![CDATA[<xml-fragment><con:entry xmlns:con="http://eviware.com/soapui/config">40</con:entry><con:entry xmlns:con="http://eviware.com/soapui/config">35</con:entry></xml-fragment>]]></row></con:configuration></con:dataSource><con:property>AddVal1</con:property><con:property>AddVal2</con:property><con:restartOnRun>true</con:restartOnRun></con:config></con:testStep><con:properties/><con:reportParameters/><con:breakPoints><con:testStepId>72a4349b-3846-4a82-84bf-ee2d89263047</con:testStepId><con:status>NONE</con:status><con:properties/></con:breakPoints><con:breakPoints><con:testStepId>1c623aa8-1365-4687-8cf8-9557279b8da0</con:testStepId><con:status>NONE</con:status><con:properties/></con:breakPoints><con:breakPoints><con:testStepId>bb44e03b-b77a-470a-8c4d-1378df9d6df0</con:testStepId><con:status>NONE</con:status><con:properties/></con:breakPoints></con:testCase><con:testCase id="b86731c1-b497-4ca5-a282-053fc91e0567" failOnError="false" failTestCaseOnErrors="true" keepSession="false" maxResults="0" name="TestCase 2(Multiply)" searchProperties="true" timeout="0" wsrmEnabled="false" wsrmVersion="1.0" wsrmAckTo="" amfAuthorisation="false" amfEndpoint="" amfLogin="" amfPassword=""><con:settings/><con:testStep type="datasource" name="DataSource3" id="27277677-a5e0-4d32-af5d-c55846dcf1bb"><con:settings/><con:config xsi:type="con:DataSourceStep" xmlns:xsi="http://www.w3.org/2001/XMLSchema-instance"><con:dataSource type="File"><con:configuration><fileName>C:/Users/bapuc/OneDrive/Documents/Selenium_Nitin Sir_Videos/API Testing/DataSource2.txt</fileName><separator>,</separator><trim>true</trim><charset>Cp1252</charset><quotedValues>false</quotedValues></con:configuration></con:dataSource><con:property>MulVal1</con:property><con:property>MulVal2</con:property><con:restartOnRun>true</con:restartOnRun></con:config></con:testStep><con:testStep type="request" name="Multiplication" id="e0b47909-c1bb-484c-ae0b-47e10ff424e2"><con:settings/><con:config xsi:type="con:RequestStep" xmlns:xsi="http://www.w3.org/2001/XMLSchema-instance"><con:interface>CalculatorSoap12</con:interface><con:operation>Multiply</con:operation><con:request name="Multiplication" id="a23718cb-8a76-45a5-a042-36c86cb81c31"><con:settings><con:setting id="com.eviware.soapui.impl.wsdl.WsdlRequest@request-headers">&lt;xml-fragment/></con:setting></con:settings><con:encoding>UTF-8</con:encoding><con:endpoint>http://www.dneonline.com/calculator.asmx</con:endpoint><con:request><![CDATA[<soap:Envelope xmlns:soap="http://www.w3.org/2003/05/soap-envelope" xmlns:tem="http://tempuri.org/">
   <soap:Header/>
   <soap:Body>
      <tem:Multiply>
         <tem:intA>${DataSource3#MulVal1}</tem:intA>
         <tem:intB>${DataSource3#MulVal2}</tem:intB>
      </tem:Multiply>
   </soap:Body>
</soap:Envelope>]]></con:request><con:assertion type="SOAP Response" id="c51d95d0-a671-4fa6-a851-a21a00964f05"/><con:credentials><con:authType>No Authorization</con:authType></con:credentials><con:jmsConfig JMSDeliveryMode="PERSISTENT"/><con:jmsPropertyConfig/><con:wsaConfig mustUnderstand="NONE" version="200508"/><con:wsrmConfig version="1.2"/></con:request></con:config></con:testStep><con:testStep type="datasourceloop" name="DataSource Loop3" id="5e0b313c-caa4-41e1-a854-ffda7b8e95f9"><con:settings/><con:config><dataSourceStep>DataSource3</dataSourceStep><targetStep>Multiplication</targetStep></con:config></con:testStep><con:properties><con:property><con:name>I</con:name><con:value>80</con:value></con:property></con:properties><con:reportParameters/></con:testCase><con:testCase id="008fd3e7-241d-46ab-aae9-120e67dbe326" failOnError="true" failTestCaseOnErrors="true" keepSession="false" maxResults="0" name="TestCase 3(Division)" searchProperties="true"><con:settings/><con:testStep type="datasource" name="DataSource4" id="6f395ff0-7560-42dc-8c35-f4f259e0a6df"><con:settings/><con:config xsi:type="con:DataSourceStep" xmlns:xsi="http://www.w3.org/2001/XMLSchema-instance"><con:dataSource type="Directory"><con:configuration><directory/><filter/><encoding/></con:configuration></con:dataSource><con:restartOnRun>true</con:restartOnRun></con:config></con:testStep><con:testStep type="request" name="Divide" id="ab0749ea-a872-4f40-8984-d07bb748a5ba"><con:settings/><con:config xsi:type="con:RequestStep" xmlns:xsi="http://www.w3.org/2001/XMLSchema-instance"><con:interface>CalculatorSoap12</con:interface><con:operation>Divide</con:operation><con:request name="Divide" id="ad5527b4-b374-4c09-9d49-892ac7f88df2"><con:settings><con:setting id="com.eviware.soapui.impl.wsdl.WsdlRequest@request-headers">&lt;xml-fragment/></con:setting></con:settings><con:encoding>UTF-8</con:encoding><con:endpoint>http://www.dneonline.com/calculator.asmx</con:endpoint><con:request><![CDATA[<soap:Envelope xmlns:soap="http://www.w3.org/2003/05/soap-envelope" xmlns:tem="http://tempuri.org/">\r
   <soap:Header/>\r
   <soap:Body>\r
      <tem:Divide>\r
         <tem:intA>10</tem:intA>\r
         <tem:intB>${#TestSuite#J}</tem:intB>\r
      </tem:Divide>\r
   </soap:Body>\r
</soap:Envelope>]]></con:request><con:assertion type="SOAP Response" id="ec3721ae-95e7-4419-a5e2-9457bb3895b5"/><con:credentials><con:authType>No Authorization</con:authType></con:credentials><con:jmsConfig JMSDeliveryMode="PERSISTENT"/><con:jmsPropertyConfig/><con:wsaConfig mustUnderstand="NONE" version="200508"/><con:wsrmConfig version="1.2"/></con:request></con:config></con:testStep><con:properties/><con:reportParameters/><con:breakPoints><con:testStepId>6f395ff0-7560-42dc-8c35-f4f259e0a6df</con:testStepId><con:status>NONE</con:status><con:properties/></con:breakPoints></con:testCase><con:properties><con:property><con:name>J</con:name><con:value>30</con:value></con:property></con:properties><con:reportParameters/></con:testSuite><con:testSuite id="108bb223-ae84-4ecf-99a6-0beabd325d23" name="TestSuite 2"><con:settings/><con:runType>SEQUENTIAL</con:runType><con:testCase id="acca5512-394a-45ee-afb3-df206d31a908" failOnError="true" failTestCaseOnErrors="true" keepSession="false" maxResults="0" name="TestCase 1(PropertyByGroovy)" searchProperties="true"><con:settings/><con:testStep type="request" name="SOAP Request_Add" id="82d5e944-310e-46d8-a4a6-ab586d1a2a92"><con:settings/><con:config xsi:type="con:RequestStep" xmlns:xsi="http://www.w3.org/2001/XMLSchema-instance"><con:interface>CalculatorSoap12</con:interface><con:operation>Add</con:operation><con:request name="SOAP Request_Add" id="aad6b9e2-5acf-47e9-8208-552982bd892a"><con:settings/><con:encoding>UTF-8</con:encoding><con:endpoint>http://www.dneonline.com/calculator.asmx</con:endpoint><con:request><![CDATA[<soap:Envelope xmlns:soap="http://www.w3.org/2003/05/soap-envelope" xmlns:tem="http://tempuri.org/">\r
   <soap:Header/>\r
   <soap:Body>\r
      <tem:Add>\r
         <tem:intA>?</tem:intA>\r
         <tem:intB>?</tem:intB>\r
      </tem:Add>\r
   </soap:Body>\r
</soap:Envelope>]]></con:request><con:assertion type="SOAP Response" id="d0026dd0-7544-4112-8f0a-d6a5efbe4b2e"/><con:credentials><con:authType>No Authorization</con:authType></con:credentials><con:jmsConfig JMSDeliveryMode="PERSISTENT"/><con:jmsPropertyConfig/><con:wsaConfig mustUnderstand="NONE" version="200508"/><con:wsrmConfig version="1.2"/></con:request></con:config></con:testStep><con:testStep type="groovy" name="Groovy Script(Get and Set Property)" id="5f68e63f-b46a-4c16-bb50-4b3e8c82c53d"><con:settings/><con:config><script>// Set Property at test case level by Groovy

i="10"
j="20"
testRunner.testCase.setPropertyValue("A",i)
testRunner.testCase.setPropertyValue("B",j)


// Set Property at test Suite level by Groovy

i="5"
j="25"
testRunner.testCase.testSuite.setPropertyValue("A",i)
testRunner.testCase.testSuite.setPropertyValue("B",j)


// Set Property at project level by Groovy

i="15"
j="35"
testRunner.testCase.testSuite.project.setPropertyValue("A",i)
testRunner.testCase.testSuite.project.setPropertyValue("B",j)

// GET Property at test case level by Groovy

log.info testRunner.testCase.getPropertyValue("A")
log.info testRunner.testCase.getPropertyValue("B")

</script></con:config></con:testStep><con:properties><con:property><con:name>A</con:name><con:value>10</con:value></con:property><con:property><con:name>B</con:name><con:value>20</con:value></con:property></con:properties><con:reportParameters/></con:testCase><con:properties><con:property><con:name>A</con:name><con:value>5</con:value></con:property><con:property><con:name>B</con:name><con:value>25</con:value></con:property></con:properties><con:reportParameters/></con:testSuite><con:requirements/><con:properties><con:property><con:name>A</con:name><con:value>15</con:value></con:property><con:property><con:name>B</con:name><con:value>35</con:value></con:property></con:properties><con:wssContainer/><con:databaseConnectionContainer/><con:oAuth2ProfileContainer/><con:oAuth1ProfileContainer/><con:reporting><con:xmlTemplates/><con:parameters/></con:reporting><con:sensitiveInformation/></con:soapui-project>